EasierMySQL/MySQLerrorTypes.py
EasierMySQL/__init__.py
EasierMySQL/easyMySQL.py
EasierSQLite/__init__.py
EasierSQLite/easySQL.py
EasierSQLite/errorTypes.py
EasierSQL-0.1.2.dist-info/LICENSE.txt
EasierSQL-0.1.2.dist-info/METADATA
EasierSQL-0.1.2.dist-info/WHEEL
EasierSQL-0.1.2.dist-info/top_level.txt
EasierSQL-0.1.2.dist-info/RECORD
