Metadata-Version: 2.1
Name: EasierSQL
Version: 0.1.2
Summary: A wrapper for SQLite and MySQL, Most of the queries wrapped into commands for ease.
Home-page: https://github.com/RefinedDev/EasierSQL
License: UNKNOWN
Platform: UNKNOWN
Classifier: Programming Language :: Python :: 3
Classifier: License :: OSI Approved :: MIT License
Classifier: Operating System :: OS Independent
Requires-Python: >=3.6
License-File: LICENSE.txt
Requires-Dist: mysql-connector
